{"_type":"export","__export_format":4,"__export_date":"2023-04-17T17:03:30.579Z","__export_source":"insomnia.desktop.app:v2023.1.0","resources":[{"_id":"req_d6d1bfa0f74841208a967bdb804220d9","parentId":"fld_ea69ed45fa5d421daaca1ee215de1ca1","modified":1681750985151,"created":1606588762654,"url":"{{base_url}}/profile","name":"Update","description":"","method":"PUT","body":{"mimeType":"application/json","text":"{\n\"name\": \"Gabriel Araujo\",\n\"contact\": \"linkedin/araujooj\"\n}"},"parameters":[],"headers":[{"name":"Content-Type","value":"application/json","id":"pair_b7edb175ee214ce9b6db9f1075c6b78e"}],"authentication":{"type":"bearer","token":"{% response 'body', 'req_7a3f4c71650d41c49666f90f3e58145e', 'b64::JC50b2tlbg==::46b', 'never', 60 %}"},"metaSortKey":-1606588762654,"isPrivate":false,"settingStoreCookies":true,"settingSendCookies":true,"settingDisableRenderRequestBody":false,"settingEncodeUrl":true,"settingRebuildPath":true,"settingFollowRedirects":"global","_type":"request"},{"_id":"fld_ea69ed45fa5d421daaca1ee215de1ca1","parentId":"fld_f25a2cc9eed14c24a66324f26d7a6b61","modified":1606587000007,"created":1606587000007,"name":"Profile","description":"","environment":{},"environmentPropertyOrder":null,"metaSortKey":-1606587000007,"_type":"request_group"},{"_id":"fld_f25a2cc9eed14c24a66324f26d7a6b61","parentId":"wrk_a495f0b673c94902973253f8a34a3acb","modified":1669743731763,"created":1605102517982,"name":"Users","description":"","environment":{},"environmentPropertyOrder":null,"metaSortKey":-1605041646363,"_type":"request_group"},{"_id":"wrk_a495f0b673c94902973253f8a34a3acb","parentId":null,"modified":1602421924232,"created":1602421924232,"name":"Kenzie Hub","description":"","scope":"design","_type":"workspace"},{"_id":"req_00683984fbf34387aaa1f67dcbdcef9e","parentId":"fld_ea69ed45fa5d421daaca1ee215de1ca1","modified":1681750982303,"created":1606587003603,"url":"{{ base_url }}/profile","name":"show","description":"","method":"GET","body":{},"parameters":[],"headers":[],"authentication":{"type":"bearer","token":"{% response 'body', 'req_7a3f4c71650d41c49666f90f3e58145e', 'b64::JC50b2tlbg==::46b', 'never', 60 %}","disabled":false},"metaSortKey":-1606587003603,"isPrivate":false,"settingStoreCookies":true,"settingSendCookies":true,"settingDisableRenderRequestBody":false,"settingEncodeUrl":true,"settingRebuildPath":true,"settingFollowRedirects":"global","_type":"request"},{"_id":"req_ea16d0e5a33647fa9c4e043042907100","parentId":"fld_f25a2cc9eed14c24a66324f26d7a6b61","modified":1636463542039,"created":1605662620156,"url":"{{ base_url }}/users/0600f0e7-9e8c-4823-8a13-1c1c7ca65f3c","name":"Get an specific user","description":"","method":"GET","body":{},"parameters":[],"headers":[],"authentication":{},"metaSortKey":-1605862412196,"isPrivate":false,"settingStoreCookies":true,"settingSendCookies":true,"settingDisableRenderRequestBody":false,"settingEncodeUrl":true,"settingRebuildPath":true,"settingFollowRedirects":"global","_type":"request"},{"_id":"req_8321d6e20cbb4208912892a17fa9606e","parentId":"fld_f25a2cc9eed14c24a66324f26d7a6b61","modified":1607109735615,"created":1605662602479,"url":"{{ base_url }}/users","name":"Get users","description":"","method":"GET","body":{},"parameters":[{"name":"perPage","value":"15","description":"","id":"pair_18900deaf8eb4ff29bc3a688eb0ec646","disabled":false},{"name":"page","value":"1","description":"","id":"pair_34965639db14490291124c513600ba1e","disabled":false},{"name":"tech","value":"Types","description":"","id":"pair_05cd4957b412458a94bfce1708ec7464","disabled":true},{"name":"","value":"","description":"","id":"pair_4e9c72409a7d44f5bf36e63ceda3ceae","disabled":true}],"headers":[],"authentication":{},"metaSortKey":-1605662602616,"isPrivate":false,"settingStoreCookies":true,"settingSendCookies":true,"settingDisableRenderRequestBody":false,"settingEncodeUrl":true,"settingRebuildPath":true,"settingFollowRedirects":"global","_type":"request"},{"_id":"req_7a3f4c71650d41c49666f90f3e58145e","parentId":"fld_f25a2cc9eed14c24a66324f26d7a6b61","modified":1632742750912,"created":1605102506103,"url":"{{ base_url }}/sessions","name":"Login","description":"","method":"POST","body":{"mimeType":"application/json","text":"{\n\t\"email\": \"gabriel@kenzie.com.br\",\n\t\"password\": \"123456\"\n}"},"parameters":[],"headers":[{"name":"Content-Type","value":"application/json","id":"pair_da91635d3dbf4c259f4e8dde3cacc116"}],"authentication":{},"metaSortKey":-1605102512093,"isPrivate":false,"settingStoreCookies":true,"settingSendCookies":true,"settingDisableRenderRequestBody":false,"settingEncodeUrl":true,"settingRebuildPath":true,"settingFollowRedirects":"global","_type":"request"},{"_id":"req_cd9e19b4a26a4e79a6d1804e637379ef","parentId":"fld_f25a2cc9eed14c24a66324f26d7a6b61","modified":1632742740937,"created":1605102511189,"url":"{{ base_url }}/users","name":"Create User","description":"","method":"POST","body":{"mimeType":"application/json","text":"{\n\"email\": \"gabriel@kenzie.com.br\",\n\"password\": \"123456\",\n\"name\": \"Filipe Gutierry\",\n\"bio\": \"Lorem ipsum dolor emet\",\n\"contact\": \"123456789\",\n\"course_module\": \"2o Módulo (Frontend avançado)\"\n}"},"parameters":[],"headers":[{"name":"Content-Type","value":"application/json","id":"pair_2a6ac3fa8cb8472294847c2fb185540d"}],"authentication":{},"metaSortKey":-1605102512043,"isPrivate":false,"settingStoreCookies":true,"settingSendCookies":true,"settingDisableRenderRequestBody":false,"settingEncodeUrl":true,"settingRebuildPath":true,"settingFollowRedirects":"global","_type":"request"},{"_id":"req_1b25964e84864f4dbb5edf5355ef1b75","parentId":"fld_a7e141338546426482b5d7de9cef1343","modified":1681750976690,"created":1605101677669,"url":"{{base_url}}/users/works","name":"Create","description":"","method":"POST","body":{"mimeType":"application/json","text":"{\n\t\"title\": \"KenzieHub\",\n\t\"description\": \"I was the backend developer of this project, and i did it using Typescript and NodeJS\",\n\t\"deploy_url\": \"https://kenziehub.me\"\n}"},"parameters":[],"headers":[{"name":"Client-ID","value":"r6rmfu6jsapswq3zklnkhbfae1r6xv","description":"","id":"pair_8ccdf551e9fc420ca51b931457e563f6"},{"name":"Content-Type","value":"application/json","id":"pair_72642c531cd14e789e843c7ec2e02f25"}],"authentication":{"type":"bearer","token":"{% response 'body', 'req_7a3f4c71650d41c49666f90f3e58145e', 'b64::JC50b2tlbg==::46b', 'never', 60 %}"},"metaSortKey":-1605071831902.5,"isPrivate":false,"settingStoreCookies":true,"settingSendCookies":true,"settingDisableRenderRequestBody":false,"settingEncodeUrl":true,"settingRebuildPath":true,"settingFollowRedirects":"global","_type":"request"},{"_id":"fld_a7e141338546426482b5d7de9cef1343","parentId":"wrk_a495f0b673c94902973253f8a34a3acb","modified":1669743728843,"created":1605101921671,"name":"Works","description":"","environment":{},"environmentPropertyOrder":null,"metaSortKey":-1605041646313,"_type":"request_group"},{"_id":"req_ff3fda1061b4404fb7865d469345a086","parentId":"fld_a7e141338546426482b5d7de9cef1343","modified":1681750974293,"created":1606958264602,"url":"{{base_url}}/users/works/e284d1ef-7d03-462d-a5d4-f733a571ebba","name":"Update","description":"","method":"PUT","body":{"mimeType":"application/json","text":"{\n\t\"title\": \"KenzieHub\"\n}"},"parameters":[],"headers":[{"name":"Content-Type","value":"application/json","id":"pair_a3bad7838b8b42938a322e09e7140d55"}],"authentication":{"type":"bearer","token":"{% response 'body', 'req_7a3f4c71650d41c49666f90f3e58145e', 'b64::JC50b2tlbg==::46b', 'never', 60 %}"},"metaSortKey":-1605071831852.5,"isPrivate":false,"settingStoreCookies":true,"settingSendCookies":true,"settingDisableRenderRequestBody":false,"settingEncodeUrl":true,"settingRebuildPath":true,"settingFollowRedirects":"global","_type":"request"},{"_id":"req_e42976fe57e84b7c9f1537f70590d338","parentId":"fld_a7e141338546426482b5d7de9cef1343","modified":1681750970992,"created":1606958289065,"url":"{{ base_url }}/users/works/48534aa3-8414-4d49-9f3b-89833f6774ff","name":"Delete","description":"","method":"DELETE","body":{},"parameters":[],"headers":[],"authentication":{"type":"bearer","token":"{% response 'body', 'req_7a3f4c71650d41c49666f90f3e58145e', 'b64::JC50b2tlbg==::46b', 'never', 60 %}"},"metaSortKey":-1605071831802.5,"isPrivate":false,"settingStoreCookies":true,"settingSendCookies":true,"settingDisableRenderRequestBody":false,"settingEncodeUrl":true,"settingRebuildPath":true,"settingFollowRedirects":"global","_type":"request"},{"_id":"req_4b072d57b2a644778e4e5ba2f16db938","parentId":"fld_c06ab32c4c80419883f50e7178463058","modified":1681750899134,"created":1605102185908,"url":"{{base_url}}/users/techs","name":"Create","description":"","method":"POST","body":{"mimeType":"application/json","text":"{\n\t\"title\": \"React\",\n\t\"status\": \"Iniciante\"\n}"},"parameters":[],"headers":[{"name":"Content-Type","value":"application/json","id":"pair_50f014a7bf8b4800bcff75bc63bf3185"}],"authentication":{"type":"bearer","token":"{% response 'body', 'req_7a3f4c71650d41c49666f90f3e58145e', 'b64::JC50b2tlbg==::46b', 'never', 60 %}"},"metaSortKey":-1606823702289,"isPrivate":false,"settingStoreCookies":true,"settingSendCookies":true,"settingDisableRenderRequestBody":false,"settingEncodeUrl":true,"settingRebuildPath":true,"settingFollowRedirects":"global","_type":"request"},{"_id":"fld_c06ab32c4c80419883f50e7178463058","parentId":"wrk_a495f0b673c94902973253f8a34a3acb","modified":1669743733374,"created":1605101997747,"name":"Techs","description":"","environment":{},"environmentPropertyOrder":null,"metaSortKey":-1605041646288,"_type":"request_group"},{"_id":"req_6ef9649668c64c3db6e97bdd9901e919","parentId":"fld_c06ab32c4c80419883f50e7178463058","modified":1681750960987,"created":1606823702239,"url":"{{base_url}}/users/techs/a50e3d20-897c-471d-83c2-c49c29f4e070","name":"Update","description":"","method":"PUT","body":{"mimeType":"application/json","text":"{\n\t\"status\": \"Avançado\"\n}"},"parameters":[],"headers":[{"name":"Content-Type","value":"application/json","id":"pair_a3bad7838b8b42938a322e09e7140d55"}],"authentication":{"type":"bearer","token":"{% response 'body', 'req_7a3f4c71650d41c49666f90f3e58145e', 'b64::JC50b2tlbg==::46b', 'never', 60 %}"},"metaSortKey":-1606823702239,"isPrivate":false,"settingStoreCookies":true,"settingSendCookies":true,"settingDisableRenderRequestBody":false,"settingEncodeUrl":true,"settingRebuildPath":true,"settingFollowRedirects":"global","_type":"request"},{"_id":"req_c7a86c2c4141411ebf03e9a9510a668e","parentId":"fld_c06ab32c4c80419883f50e7178463058","modified":1681750963318,"created":1606945052958,"url":"{{ base_url }}/users/techs/9f53cf10-3fe4-4e01-86aa-2c85eca7fb1","name":"Delete","description":"","method":"DELETE","body":{},"parameters":[],"headers":[],"authentication":{"type":"bearer","token":"{% response 'body', 'req_7a3f4c71650d41c49666f90f3e58145e', 'b64::JC50b2tlbg==::46b', 'never', 60 %}"},"metaSortKey":-1606823702189,"isPrivate":false,"settingStoreCookies":true,"settingSendCookies":true,"settingDisableRenderRequestBody":false,"settingEncodeUrl":true,"settingRebuildPath":true,"settingFollowRedirects":"global","_type":"request"},{"_id":"env_06627449ae0e4746d281efc70a38f7bd188112b7","parentId":"wrk_a495f0b673c94902973253f8a34a3acb","modified":1636391116513,"created":1602421924271,"name":"Base Environment","data":{},"dataPropertyOrder":{},"color":null,"isPrivate":false,"metaSortKey":1602421924271,"_type":"environment"},{"_id":"jar_06627449ae0e4746d281efc70a38f7bd188112b7","parentId":"wrk_a495f0b673c94902973253f8a34a3acb","modified":1605026229009,"created":1602421924272,"name":"Default Jar","cookies":[{"key":"__cfduid","value":"da91ca01b0f269799405a11c6b56e17371605026228","expires":"2020-12-10T16:37:08.000Z","domain":"igdb.com","path":"/","secure":true,"httpOnly":true,"extensions":["SameSite=Lax"],"hostOnly":false,"creation":"2020-11-10T16:37:09.000Z","lastAccessed":"2020-11-10T16:37:09.000Z","id":"9363628542240467"}],"_type":"cookie_jar"},{"_id":"spc_f507493235ec41eeb21ecac945714c70","parentId":"wrk_a495f0b673c94902973253f8a34a3acb","modified":1669743752169,"created":1602421924234,"fileName":"Kenzie Hub API","contents":"","contentType":"yaml","_type":"api_spec"},{"_id":"env_ea429a0b1aa6492ebd6d5602e9435f47","parentId":"env_06627449ae0e4746d281efc70a38f7bd188112b7","modified":1681750946057,"created":1606434544462,"name":"Production","data":{"base_url":"https://kenziehub.herokuapp.com"},"dataPropertyOrder":{"&":["base_url"]},"color":null,"isPrivate":false,"metaSortKey":1606434544462,"_type":"environment"},{"_id":"env_780a6c1d78404375a6c682d1f9c3de42","parentId":"env_06627449ae0e4746d281efc70a38f7bd188112b7","modified":1681750950870,"created":1606434557354,"name":"Development","data":{"base_url":"http://localhost:3333"},"dataPropertyOrder":{"&":["base_url"]},"color":null,"isPrivate":false,"metaSortKey":1606434557354,"_type":"environment"}]}
